spoa.cpython-38-x86_64-linux-gnu.so
pyspoa-0.3.1.dist-info/LICENSE
pyspoa-0.3.1.dist-info/METADATA
pyspoa-0.3.1.dist-info/WHEEL
pyspoa-0.3.1.dist-info/top_level.txt
pyspoa-0.3.1.dist-info/RECORD
