Metadata-Version: 2.1
Name: pyspoa
Version: 0.3.1
Summary: Python bindings to spoa
Home-page: https://github.com/nanoporetech/pyspoa
Author: Oxford Nanoporetech Technologies, Ltd.
Author-email: support@nanoporetech.com
License: UNKNOWN
Platform: UNKNOWN
